{
  "name": "product",
  "plural": "products",
  "base": "PersistedModel",
  "idInjection": true,
  "dataSource": "mysqlDs",
  "properties": {
    "title": {
      "type": "string",
      "required": true
    },
    "isbn13": {
      "type": "string"
    },
    "config": {
      "type": "string"
    },
    "productId": {
      "type": "number",
      "id": true
    },
    "nCodes":{
      "type": "number"
    }
  },
  "validations": [],
  "relations": {
    "availableCodes":{
        "type": "hasMany",
        "model": "availableCodes",
        "foreignKey": "productId"
    }
    },
  "acls": [],
  "methods": []
}
