{
  "mydbZ": {
    "name": "mydbZ",
    "connector": "memory"
  },
  "mydb": {
    "host": "localhost",
    "port": 5432,
    "database": "dispense",
    "password": "loopback",
    "name": "mydb",
    "user": "loopback",
    "connector": "postgresql"
  },
  "emailDs": {
    "name": "emailDs",
    "connector": "mail",
    "transports": [
      {
        "type": "smtp",
        "host": "smtp.gmail.com",
        "secure": true,
        "port": 465,
        "tls": {
          "rejectUnauthorized": false
        },
        "auth": {
          "user": "dispense.wiley@gmail.com",
          "pass": "wiley123"
        }
      }
    ]
  }
}
